genrl/__init__.py
genrl/agents/__init__.py
genrl/agents/bandits/__init__.py
genrl/agents/bandits/contextual/__init__.py
genrl/agents/bandits/contextual/base.py
genrl/agents/bandits/contextual/bootstrap_neural.py
genrl/agents/bandits/contextual/fixed.py
genrl/agents/bandits/contextual/linpos.py
genrl/agents/bandits/contextual/neural_greedy.py
genrl/agents/bandits/contextual/neural_linpos.py
genrl/agents/bandits/contextual/neural_noise_sampling.py
genrl/agents/bandits/contextual/variational.py
genrl/agents/bandits/contextual/common/__init__.py
genrl/agents/bandits/contextual/common/base_model.py
genrl/agents/bandits/contextual/common/bayesian.py
genrl/agents/bandits/contextual/common/neural.py
genrl/agents/bandits/contextual/common/transition.py
genrl/agents/bandits/multiarmed/__init__.py
genrl/agents/bandits/multiarmed/base.py
genrl/agents/bandits/multiarmed/bayesian.py
genrl/agents/bandits/multiarmed/bernoulli_mab.py
genrl/agents/bandits/multiarmed/epsgreedy.py
genrl/agents/bandits/multiarmed/gaussian_mab.py
genrl/agents/bandits/multiarmed/gradient.py
genrl/agents/bandits/multiarmed/thompson.py
genrl/agents/bandits/multiarmed/ucb.py
genrl/agents/classical/__init__.py
genrl/agents/classical/qlearning/__init__.py
genrl/agents/classical/qlearning/qlearning.py
genrl/agents/classical/sarsa/__init__.py
genrl/agents/classical/sarsa/sarsa.py
genrl/agents/deep/__init__.py
genrl/agents/deep/a2c/__init__.py
genrl/agents/deep/a2c/a2c.py
genrl/agents/deep/base/__init__.py
genrl/agents/deep/base/base.py
genrl/agents/deep/base/offpolicy.py
genrl/agents/deep/base/onpolicy.py
genrl/agents/deep/ddpg/__init__.py
genrl/agents/deep/ddpg/ddpg.py
genrl/agents/deep/dqn/__init__.py
genrl/agents/deep/dqn/base.py
genrl/agents/deep/dqn/categorical.py
genrl/agents/deep/dqn/double.py
genrl/agents/deep/dqn/dueling.py
genrl/agents/deep/dqn/noisy.py
genrl/agents/deep/dqn/prioritized.py
genrl/agents/deep/dqn/utils.py
genrl/agents/deep/ppo1/__init__.py
genrl/agents/deep/ppo1/ppo1.py
genrl-0.0.2.dist-info/AUTHORS.rst
genrl-0.0.2.dist-info/LICENSE
genrl-0.0.2.dist-info/METADATA
genrl-0.0.2.dist-info/WHEEL
genrl-0.0.2.dist-info/top_level.txt
genrl-0.0.2.dist-info/RECORD
