Metadata-Version: 2.1
Name: genrl
Version: 0.0.2
Summary: A PyTorch reinforcement learning library for generalizable and reproducible algorithm implementations.
Home-page: https://github.com/SforAiDl/genrl
Author: Society for Artificial Intelligence and Deep Learning
Author-email: ajaysubramanian110@gmail.com
License: MIT
Project-URL: Source, https://github.com/SforAiDl/genrl
Keywords: reinforcement learning,pytorch,machine learning,deep learning
Platform: UNKNOWN
Classifier: Development Status :: 5 - Production/Stable
Classifier: Intended Audience :: Developers
Classifier: Intended Audience :: Science/Research
Classifier: License :: OSI Approved :: MIT License
Classifier: Natural Language :: English
Classifier: Operating System :: OS Independent
Classifier: Programming Language :: Python
Classifier: Programming Language :: Python :: 3.6
Classifier: Programming Language :: Python :: 3.7
Classifier: Programming Language :: Python :: 3.8
Classifier: Topic :: Software Development
Classifier: Topic :: Software Development :: Libraries :: Python Modules
Classifier: Topic :: Scientific/Engineering :: Artificial Intelligence
Requires-Python: >=3.6
Requires-Dist: atari-py (==0.2.6)
Requires-Dist: box2d-py (==2.3.8)
Requires-Dist: certifi (==2019.11.28)
Requires-Dist: cloudpickle (==1.3.0)
Requires-Dist: future (==0.18.2)
Requires-Dist: gym (==0.17.1)
Requires-Dist: numpy (==1.18.2)
Requires-Dist: opencv-python (==4.2.0.34)
Requires-Dist: pandas (==1.0.4)
Requires-Dist: Pillow (==7.1.0)
Requires-Dist: pyglet (==1.5.0)
Requires-Dist: scipy (==1.4.1)
Requires-Dist: six (==1.14.0)
Requires-Dist: matplotlib (==3.2.1)
Requires-Dist: pytest (==5.4.1)
Requires-Dist: torch (==1.4.0)
Requires-Dist: torchvision (==0.5.0)
Requires-Dist: tensorflow-tensorboard (==1.5.1)
Requires-Dist: tensorboard (==1.15.0)
Requires-Dist: pre-commit (==2.4.0)
Requires-Dist: importlib-resources (==1.0.1)
Requires-Dist: setuptools (==41.0.0)
